simple_retry_listener/SimpleRetryListener.py
simple_retry_listener/__init__.py
simple_retry_listener/core.py
simple_retry_listener/gui.py
simple_retry_listener-1.0.0.dist-info/METADATA
simple_retry_listener-1.0.0.dist-info/WHEEL
simple_retry_listener-1.0.0.dist-info/top_level.txt
simple_retry_listener-1.0.0.dist-info/RECORD
