Metadata-Version: 2.1
Name: simple-retry-listener
Version: 1.0.0
Summary: A Robot Framework listener for interactive retry of failed keywords
Home-page: https://github.com/tsuri/simple-retry-listener
Author: Suriya
Author-email: tsuriya321@gmail.com
License: MIT
Keywords: robotframework testing listener retry
Classifier: Development Status :: 4 - Beta
Classifier: Intended Audience :: Developers
Classifier: License :: OSI Approved :: MIT License
Classifier: Programming Language :: Python :: 3
Classifier: Programming Language :: Python :: 3.7
Classifier: Programming Language :: Python :: 3.8
Classifier: Programming Language :: Python :: 3.9
Classifier: Programming Language :: Python :: 3.10
Classifier: Topic :: Software Development :: Testing
Classifier: Framework :: Robot Framework
Requires-Dist: robotframework>=6.1.1
